pyjexl/__init__.py
pyjexl/analysis.py
pyjexl/evaluator.py
pyjexl/exceptions.py
pyjexl/extended_grammar.py
pyjexl/jexl.py
pyjexl/jexl_extended.py
pyjexl/operators.py
pyjexl/parser.py
pyjexl_extended-0.2.2.dist-info/licenses/LICENSE
pyjexl_extended-0.2.2.dist-info/METADATA
pyjexl_extended-0.2.2.dist-info/WHEEL
pyjexl_extended-0.2.2.dist-info/top_level.txt
pyjexl_extended-0.2.2.dist-info/RECORD
