Metadata-Version: 2.4
Name: pyjexl-extended
Version: 0.2.2
Summary: A JEXL parser and evaluator with extended grammar (80+ built-in functions and transforms).
Author-email: nikoraes <niko.raes@gmail.com>
License: Copyright (c) 2016 Michael Kelly.
Project-URL: Homepage, https://github.com/konnektr-io/pyjexl-extended
Project-URL: Repository, https://github.com/konnektr-io/pyjexl-extended
Project-URL: Playground, https://jexl-playground.konnektr.io/
Keywords: jexl,expression,parser,grammar,extended
Classifier: Development Status :: 4 - Beta
Classifier: Intended Audience :: Developers
Classifier: Topic :: Software Development
Classifier: License :: OSI Approved :: MIT License
Classifier: Programming Language :: Python :: 3.6
Classifier: Programming Language :: Python :: 3.7
Classifier: Programming Language :: Python :: 3.8
Classifier: Programming Language :: Python :: 3.9
Classifier: Programming Language :: Python :: 3.10
Classifier: Programming Language :: Python :: 3.11
Classifier: Programming Language :: Python :: 3.12
Requires-Python: >=3.6
License-File: LICENSE
Requires-Dist: parsimonious
Requires-Dist: future
Requires-Dist: python-dateutil
Requires-Dist: pytz
Dynamic: license-file
